portfolio/__init__.py
portfolio/portfolio_report.py
tests/__init__.py
tests/conftest.py
tests/test_io.py
tests/test_portfolio_report.py
portfolio_report_Ross_McCandless-0.0.1.dist-info/LICENSE
portfolio_report_Ross_McCandless-0.0.1.dist-info/METADATA
portfolio_report_Ross_McCandless-0.0.1.dist-info/WHEEL
portfolio_report_Ross_McCandless-0.0.1.dist-info/top_level.txt
portfolio_report_Ross_McCandless-0.0.1.dist-info/RECORD
