Metadata-Version: 2.1
Name: portfolio-report-Ross-McCandless
Version: 0.0.1
Summary: Stock portfolio report program
Home-page: https://github.com/sheridan-python/assignment-7-Ross-McCandless
Author: Ross McCandless
Author-email: rmccandless1100@conestogac.on.ca
License: UNKNOWN
Platform: UNKNOWN
Classifier: Programming Language :: Python :: 3
Classifier: License :: OSI Approved :: MIT License
Classifier: Operating System :: OS Independent
Requires-Python: >=3.6
